plot_plasmids/__init__.py
plot_plasmids/main.py
plot_plasmids/prep.py
plot_plasmids-0.2.1.dist-info/licenses/LICENSE
plot_plasmids-0.2.1.dist-info/METADATA
plot_plasmids-0.2.1.dist-info/WHEEL
plot_plasmids-0.2.1.dist-info/entry_points.txt
plot_plasmids-0.2.1.dist-info/top_level.txt
plot_plasmids-0.2.1.dist-info/RECORD
