Metadata-Version: 2.4
Name: plot-plasmids
Version: 0.2.1
Summary: A tool to generate PCoA or NMDS plots for plasmids.
Home-page: https://github.com/motroy/plot_plasmids
Author: motroy
Author-email: motroy@email.com
License-File: LICENSE
Requires-Dist: pandas
Requires-Dist: numpy
Requires-Dist: scikit-bio
Requires-Dist: scikit-learn
Requires-Dist: matplotlib
Requires-Dist: seaborn
Requires-Dist: adjusttext
Dynamic: author
Dynamic: author-email
Dynamic: description
Dynamic: description-content-type
Dynamic: home-page
Dynamic: license-file
Dynamic: requires-dist
Dynamic: summary
